[{"name":"Coffee - Egg Nog Capuccino","price":29.99,"shopify_product_id":0},
{"name":"The Pop Shoppe - Root Beer","price":35.9,"shopify_product_id":0},
{"name":"Pastry - Carrot Muffin - Mini","price":41.98,"shopify_product_id":0},
{"name":"Cup - 3.5oz, Foam","price":36.02,"shopify_product_id":0},
{"name":"Glucose","price":23.12,"shopify_product_id":0},
{"name":"Pastry - Raisin Muffin - Mini","price":20.49,"shopify_product_id":0},
{"name":"Wine - Prem Select Charddonany","price":33.84,"shopify_product_id":0},
{"name":"Tomatoes - Vine Ripe, Yellow","price":34.62,"shopify_product_id":0},
{"name":"Cherries - Bing, Canned","price":33.61,"shopify_product_id":0},
{"name":"Soup - Campbells Tomato Ravioli","price":34.17,"shopify_product_id":0},
{"name":"Tomatoes - Hot House","price":38.05,"shopify_product_id":0},
{"name":"Wine - Alsace Riesling Reserve","price":35.26,"shopify_product_id":0},
{"name":"Salt - Table","price":30.22,"shopify_product_id":0},
{"name":"Island Oasis - Lemonade","price":9.99,"shopify_product_id":0},
{"name":"Lentils - Green Le Puy","price":22.37,"shopify_product_id":0},
{"name":"Beer - Paulaner Hefeweisse","price":26.34,"shopify_product_id":0},
{"name":"Compound - Rum","price":35.24,"shopify_product_id":0},
{"name":"Wine - Bourgogne 2002, La","price":27.51,"shopify_product_id":0},
{"name":"Napkin - Beverge, White 2 - Ply","price":26.51,"shopify_product_id":0},
{"name":"Chicken - Whole Roasting","price":21.8,"shopify_product_id":0},
{"name":"Pastry - Choclate Baked","price":7.04,"shopify_product_id":0},
{"name":"Beef - Prime Rib Aaa","price":34.28,"shopify_product_id":0},
{"name":"Wine - Chablis J Moreau Et Fils","price":10.37,"shopify_product_id":0},
{"name":"Muffin Batt - Ban Dream Zero","price":35.53,"shopify_product_id":0},
{"name":"Roe - Lump Fish, Black","price":24.3,"shopify_product_id":0},
{"name":"Fennel - Seeds","price":34.06,"shopify_product_id":0},
{"name":"Wine - Clavet Saint Emilion","price":21.19,"shopify_product_id":0},
{"name":"Potatoes - Fingerling 4 Oz","price":35.5,"shopify_product_id":0},
{"name":"Chicken - Whole Fryers","price":32.21,"shopify_product_id":0},
{"name":"Lemonade - Black Cherry, 591 Ml","price":23.71,"shopify_product_id":0},
{"name":"Grapes - Black","price":36.49,"shopify_product_id":0},
{"name":"Puff Pastry - Slab","price":28.97,"shopify_product_id":0},
{"name":"Radish - Black, Winter, Organic","price":22.48,"shopify_product_id":0},
{"name":"Pepper - Chillies, Crushed","price":34.19,"shopify_product_id":0},
{"name":"Pepper - Yellow Bell","price":31.16,"shopify_product_id":0},
{"name":"Bread - Pumpernickel","price":18.98,"shopify_product_id":0},
{"name":"Quail - Whole, Bone - In","price":24.93,"shopify_product_id":0},
{"name":"Peas - Pigeon, Dry","price":23.55,"shopify_product_id":0},
{"name":"Apple - Granny Smith","price":25.17,"shopify_product_id":0},
{"name":"Doilies - 12, Paper","price":41.36,"shopify_product_id":0},
{"name":"Cheese - Cheddar, Old White","price":32.24,"shopify_product_id":0},
{"name":"Sauce - Caesar Dressing","price":35.87,"shopify_product_id":0},
{"name":"Bread - Bistro White","price":17.07,"shopify_product_id":0},
{"name":"Oil - Olive Bertolli","price":17.82,"shopify_product_id":0},
{"name":"Radish - Black, Winter, Organic","price":33.11,"shopify_product_id":0},
{"name":"Pizza Pizza Dough","price":30.33,"shopify_product_id":0},
{"name":"Wine - Casillero Deldiablo","price":27.59,"shopify_product_id":0},
{"name":"French Pastry - Mini Chocolate","price":22.65,"shopify_product_id":0},
{"name":"Hot Choc Vending","price":14.04,"shopify_product_id":0},
{"name":"Peach - Fresh","price":25.24,"shopify_product_id":0},
{"name":"Wine - Bourgogne 2002, La","price":23.24,"shopify_product_id":0},
{"name":"Wine - Magnotta - Belpaese","price":7.19,"shopify_product_id":0},
{"name":"Coconut - Whole","price":13.4,"shopify_product_id":0},
{"name":"Wine - Guy Sage Touraine","price":21.7,"shopify_product_id":0},
{"name":"Juice - Clam, 46 Oz","price":17.63,"shopify_product_id":0},
{"name":"Table Cloth 54x54 Colour","price":16.66,"shopify_product_id":0},
{"name":"Bread Cranberry Foccacia","price":8.72,"shopify_product_id":0},
{"name":"Ice Cream Bar - Hagen Daz","price":10.45,"shopify_product_id":0},
{"name":"Salmon - Atlantic, Fresh, Whole","price":22.67,"shopify_product_id":0},
{"name":"Wine - Vovray Sec Domaine Huet","price":28.75,"shopify_product_id":0},
{"name":"Cherries - Frozen","price":24.4,"shopify_product_id":0},
{"name":"Lamb - Racks, Frenched","price":11.61,"shopify_product_id":0},
{"name":"Table Cloth 144x90 White","price":30.33,"shopify_product_id":0},
{"name":"Beans - Kidney, Red Dry","price":27.4,"shopify_product_id":0},
{"name":"Garbage Bags - Black","price":22.0,"shopify_product_id":0},
{"name":"Soup - Campbells Beef Stew","price":37.88,"shopify_product_id":0},
{"name":"Wine - Red, Mosaic Zweigelt","price":29.85,"shopify_product_id":0},
{"name":"Turkey Tenderloin Frozen","price":27.64,"shopify_product_id":0},
{"name":"Fudge - Chocolate Fudge","price":24.69,"shopify_product_id":0},
{"name":"Salmon - Atlantic, Skin On","price":27.6,"shopify_product_id":0},
{"name":"Wine - Two Oceans Cabernet","price":18.57,"shopify_product_id":0},
{"name":"Mousse - Passion Fruit","price":16.32,"shopify_product_id":0},
{"name":"Sprite, Diet - 355ml","price":37.37,"shopify_product_id":0},
{"name":"Capicola - Hot","price":42.82,"shopify_product_id":0},
{"name":"Beer - Muskoka Cream Ale","price":38.51,"shopify_product_id":0},
{"name":"Puree - Pear","price":21.98,"shopify_product_id":0},
{"name":"Plate - Foam, Bread And Butter","price":27.99,"shopify_product_id":0},
{"name":"Rice - Aborio","price":35.96,"shopify_product_id":0},
{"name":"Sorrel - Fresh","price":20.4,"shopify_product_id":0},
{"name":"Squid - Breaded","price":40.05,"shopify_product_id":0},
{"name":"Beef - Tongue, Fresh","price":14.26,"shopify_product_id":0},
{"name":"Jerusalem Artichoke","price":30.44,"shopify_product_id":0},
{"name":"Chervil - Fresh","price":23.18,"shopify_product_id":0},
{"name":"Mousse - Passion Fruit","price":16.81,"shopify_product_id":0},
{"name":"Banana Turning","price":24.23,"shopify_product_id":0},
{"name":"Chinese Lemon Pork","price":33.69,"shopify_product_id":0},
{"name":"Sparkling Wine - Rose, Freixenet","price":20.9,"shopify_product_id":0},
{"name":"Steampan - Foil","price":23.92,"shopify_product_id":0},
{"name":"Sauce - Apple, Unsweetened","price":15.45,"shopify_product_id":0},
{"name":"Lettuce - Baby Salad Greens","price":9.08,"shopify_product_id":0},
{"name":"Brocolinni - Gaylan, Chinese","price":38.47,"shopify_product_id":0},
{"name":"Wine - Jackson Triggs Okonagan","price":25.94,"shopify_product_id":0},
{"name":"Juice - Orangina","price":21.2,"shopify_product_id":0},
{"name":"Red Currants","price":19.99,"shopify_product_id":0},
{"name":"Cranberry Foccacia","price":7.22,"shopify_product_id":0},
{"name":"Oil - Coconut","price":35.42,"shopify_product_id":0},
{"name":"Mushroom Morel Fresh","price":23.22,"shopify_product_id":0},
{"name":"Wine - Lamancha Do Crianza","price":27.65,"shopify_product_id":0},
{"name":"Beef - Top Butt Aaa","price":28.59,"shopify_product_id":0},
{"name":"Tray - 12in Rnd Blk","price":24.83,"shopify_product_id":0},
{"name":"Cheese - Grie Des Champ","price":24.53,"shopify_product_id":0},
{"name":"Muffin Hinge - 211n","price":13.89,"shopify_product_id":0},
{"name":"Cookie - Oreo 100x2","price":32.95,"shopify_product_id":0},
{"name":"Soup - Campbells Mac N Cheese","price":28.01,"shopify_product_id":0},
{"name":"Juice - Tomato, 48 Oz","price":17.3,"shopify_product_id":0},
{"name":"Huck Towels White","price":24.89,"shopify_product_id":0},
{"name":"Sauce - Sesame Thai Dressing","price":36.4,"shopify_product_id":0},
{"name":"Kippers - Smoked","price":7.59,"shopify_product_id":0},
{"name":"Lamb - Whole, Frozen","price":21.45,"shopify_product_id":0},
{"name":"Yoghurt Tubes","price":42.36,"shopify_product_id":0},
{"name":"Beef Ground Medium","price":17.3,"shopify_product_id":0},
{"name":"Potatoes - Idaho 80 Count","price":39.81,"shopify_product_id":0},
{"name":"Lettuce - Lambs Mash","price":11.06,"shopify_product_id":0},
{"name":"Fish - Bones","price":8.1,"shopify_product_id":0},
{"name":"Pop Shoppe Cream Soda","price":28.3,"shopify_product_id":0},
{"name":"Fond - Chocolate","price":41.84,"shopify_product_id":0},
{"name":"Pea - Snow","price":41.9,"shopify_product_id":0},
{"name":"Lotus Rootlets - Canned","price":22.81,"shopify_product_id":0},
{"name":"Wine - White, Antinore Orvieto","price":19.15,"shopify_product_id":0},
{"name":"Juice - Happy Planet","price":23.05,"shopify_product_id":0},
{"name":"Apple - Fuji","price":28.24,"shopify_product_id":0},
{"name":"Beer - Original Organic Lager","price":21.6,"shopify_product_id":0},
{"name":"Wine - Acient Coast Caberne","price":9.11,"shopify_product_id":0},
{"name":"Wine - George Duboeuf Rose","price":8.98,"shopify_product_id":0},
{"name":"Heavy Duty Dust Pan","price":16.17,"shopify_product_id":0},
{"name":"Beets - Mini Golden","price":34.5,"shopify_product_id":0},
{"name":"Appetizer - Shrimp Puff","price":42.27,"shopify_product_id":0},
{"name":"Lemonade - Pineapple Passion","price":17.76,"shopify_product_id":0},
{"name":"Chips - Miss Vickies","price":16.88,"shopify_product_id":0},
{"name":"Island Oasis - Raspberry","price":38.28,"shopify_product_id":0},
{"name":"Mushrooms - Honey","price":29.77,"shopify_product_id":0},
{"name":"Beef - Top Butt Aaa","price":10.22,"shopify_product_id":0},
{"name":"Wine - Tribal Sauvignon","price":18.71,"shopify_product_id":0},
{"name":"Pastry - Key Limepoppy Seed Tea","price":28.66,"shopify_product_id":0},
{"name":"Flour - Semolina","price":39.32,"shopify_product_id":0},
{"name":"Wine - White, Pelee Island","price":11.93,"shopify_product_id":0},
{"name":"Nutmeg - Ground","price":9.49,"shopify_product_id":0},
{"name":"Jolt Cola - Red Eye","price":34.41,"shopify_product_id":0},
{"name":"Wine - Riesling Dr. Pauly","price":28.36,"shopify_product_id":0},
{"name":"Bread - White Mini Epi","price":33.36,"shopify_product_id":0},
{"name":"Pepper - Gypsy Pepper","price":14.05,"shopify_product_id":0},
{"name":"Compound - Passion Fruit","price":18.08,"shopify_product_id":0},
{"name":"Soup - Knorr, Chicken Gumbo","price":22.75,"shopify_product_id":0},
{"name":"Nantucket Orange Juice","price":7.72,"shopify_product_id":0},
{"name":"Pastry - Trippleberry Muffin - Mini","price":28.8,"shopify_product_id":0},
{"name":"Sausage - Meat","price":24.6,"shopify_product_id":0},
{"name":"Bar Nature Valley","price":22.45,"shopify_product_id":0},
{"name":"Couscous","price":24.88,"shopify_product_id":0},
{"name":"Wine - Red, Pinot Noir, Chateau","price":38.05,"shopify_product_id":0},
{"name":"Chicken - Whole Roasting","price":35.37,"shopify_product_id":0}]